pyeg/__init__.py
pyeg/parser.py
pyeg-0.1.1.dist-info/LICENSE
pyeg-0.1.1.dist-info/METADATA
pyeg-0.1.1.dist-info/WHEEL
pyeg-0.1.1.dist-info/top_level.txt
pyeg-0.1.1.dist-info/RECORD
