Metadata-Version: 2.2
Name: pyeg
Version: 0.1.1
Summary: A simple pyeg parser
Home-page: https://github.com/yourusername/pyeg
Author: Your Name
Author-email: Your Name <your.email@example.com>
License: MIT License
Requires-Python: >=3.6
License-File: LICENSE
Requires-Dist: lark-parser
Dynamic: author
Dynamic: home-page
Dynamic: requires-python
